mkdocs_pyscript/__init__.py
mkdocs_pyscript/plugin.py
mkdocs_pyscript/dist/css/pyrepl.css
mkdocs_pyscript/dist/js/makeblocks.js
mkdocs_pyscript/dist/js/mini-coi.js
tests/__init__.py
tests/conftest.py
tests/support.py
tests/test_dynamic.py
tests/test_static.py
mkdocs_pyscript-0.2.1.dist-info/LICENSE
mkdocs_pyscript-0.2.1.dist-info/METADATA
mkdocs_pyscript-0.2.1.dist-info/WHEEL
mkdocs_pyscript-0.2.1.dist-info/entry_points.txt
mkdocs_pyscript-0.2.1.dist-info/top_level.txt
mkdocs_pyscript-0.2.1.dist-info/RECORD
