Metadata-Version: 2.1
Name: mkdocs-pyscript
Version: 0.2.1
Summary: Add PyScript to your mkdocs site
Home-page: https://github.com/jeffersglass/mkdocs-pyscript
Author: Jeff Glass
Author-email: mail@jeff.glass
License: APACHE
Keywords: mkdocs,pyscript
Classifier: Development Status :: 4 - Beta
Classifier: Intended Audience :: Developers
Classifier: Intended Audience :: Information Technology
Classifier: License :: OSI Approved :: MIT License
Classifier: Programming Language :: Python
Classifier: Programming Language :: Python :: 3 :: Only
Classifier: Programming Language :: Python :: 3.8
Classifier: Programming Language :: Python :: 3.9
Classifier: Programming Language :: Python :: 3.10
Classifier: Programming Language :: Python :: 3.11
Requires-Python: >=3.8
License-File: LICENSE
Requires-Dist: mkdocs >=1.4.0
Requires-Dist: beautifulsoup4 >=4.1
